markdown_fenced_code_tabs_next/__init__.py
markdown_fenced_code_tabs_next/base-template.html
markdown_fenced_code_tabs_next/bootstrap3-template.html
markdown_fenced_code_tabs_next/bootstrap4-template.html
markdown_fenced_code_tabs_next/bootstrap5-template.html
markdown_fenced_code_tabs_next/default-template.html
markdown_fenced_code_tabs_next/tab.py
markdown_fenced_code_tabs_next/util.py
markdown_fenced_code_tabs_next-1.1.1.dist-info/LICENSE
markdown_fenced_code_tabs_next-1.1.1.dist-info/METADATA
markdown_fenced_code_tabs_next-1.1.1.dist-info/WHEEL
markdown_fenced_code_tabs_next-1.1.1.dist-info/top_level.txt
markdown_fenced_code_tabs_next-1.1.1.dist-info/RECORD
